LICENSE
README.md
setup.py
baidufanyi/__init__.py
baidufanyi.egg-info/PKG-INFO
baidufanyi.egg-info/SOURCES.txt
baidufanyi.egg-info/dependency_links.txt
baidufanyi.egg-info/requires.txt
baidufanyi.egg-info/top_level.txt