Metadata-Version: 2.1
Name: baidufanyi
Version: 0.3.0
Summary: A simple SDK for the Baidu Translation API (unofficial)
Home-page: https://github.com/xuanzhi33/baidufanyi
Author: xuanzhi33
Author-email: xuanzhi33@qq.com
License: GPL-3.0
Platform: UNKNOWN
Classifier: Programming Language :: Python :: 3
Classifier: License :: OSI Approved :: GNU General Public License v3 (GPLv3)
Classifier: Operating System :: OS Independent
Requires-Python: >=3.6
License-File: LICENSE
